odoo8_addon_stock_split_picking-8.0.1.1.0-py2.7-nspkg.pth
odoo8_addon_stock_split_picking-8.0.1.1.0.dist-info/METADATA
odoo8_addon_stock_split_picking-8.0.1.1.0.dist-info/RECORD
odoo8_addon_stock_split_picking-8.0.1.1.0.dist-info/WHEEL
odoo8_addon_stock_split_picking-8.0.1.1.0.dist-info/namespace_packages.txt
odoo8_addon_stock_split_picking-8.0.1.1.0.dist-info/top_level.txt
odoo_addons/stock_split_picking/README.rst
odoo_addons/stock_split_picking/__init__.py
odoo_addons/stock_split_picking/__openerp__.py
odoo_addons/stock_split_picking/i18n/ca.po
odoo_addons/stock_split_picking/i18n/de.po
odoo_addons/stock_split_picking/i18n/es.po
odoo_addons/stock_split_picking/i18n/es_AR.po
odoo_addons/stock_split_picking/i18n/es_MX.po
odoo_addons/stock_split_picking/i18n/fi.po
odoo_addons/stock_split_picking/i18n/fr.po
odoo_addons/stock_split_picking/i18n/hr.po
odoo_addons/stock_split_picking/i18n/it.po
odoo_addons/stock_split_picking/i18n/pt.po
odoo_addons/stock_split_picking/i18n/pt_BR.po
odoo_addons/stock_split_picking/i18n/sl.po
odoo_addons/stock_split_picking/i18n/tr.po
odoo_addons/stock_split_picking/i18n/tr_TR.po
odoo_addons/stock_split_picking/model/__init__.py
odoo_addons/stock_split_picking/model/stock.py
odoo_addons/stock_split_picking/static/description/icon.png
odoo_addons/stock_split_picking/test/test_assigned_picking_split.yml
odoo_addons/stock_split_picking/test/test_picking_split.yml
odoo_addons/stock_split_picking/test/test_picking_split_two_move_lines.yml
odoo_addons/stock_split_picking/view/stock_partial_picking.xml
